README.rst
setup.py
starman/__init__.py
starman/kalman.py
starman/linearsystem.py
starman/rts.py
starman/slh.py
starman/stats.py
starman/util.py
starman.egg-info/PKG-INFO
starman.egg-info/SOURCES.txt
starman.egg-info/dependency_links.txt
starman.egg-info/requires.txt
starman.egg-info/top_level.txt
test/test_import.py
test/test_kalman.py
test/test_linearsystem.py
test/test_slh.py
test/test_stats.py
test/test_util.py