Metadata-Version: 1.1
Name: starman
Version: 1.0.0
Summary: A library which implements algorithms of use when trying to track the true state of one or more systems over time in the presence of noisy observations.
Home-page: https://github.com/rjw57/starman
Author: Rich Wareham
Author-email: rich.starman@richwareham.com
License: MIT
Platform: UNKNOWN
Classifier: Development Status :: 4 - Beta
Classifier: Environment :: Console
Classifier: Intended Audience :: Developers
Classifier: Intended Audience :: Science/Research
Classifier: License :: OSI Approved :: MIT License
Classifier: Operating System :: POSIX
Classifier: Topic :: Scientific/Engineering
Classifier: Programming Language :: Python :: 2
Classifier: Programming Language :: Python :: 3
